nectar2p/__init__.py
nectar2p/__main__.py
nectar2p/nectar_receiver.py
nectar2p/nectar_sender.py
nectar2p/encryption/__init__.py
nectar2p/encryption/aes_handler.py
nectar2p/encryption/rsa_handler.py
nectar2p/networking/__init__.py
nectar2p/networking/connection.py
nectar2p/networking/nat_traversal.py
nectar2p-1.2.0.dist-info/licenses/LICENSE
nectar2p-1.2.0.dist-info/METADATA
nectar2p-1.2.0.dist-info/WHEEL
nectar2p-1.2.0.dist-info/top_level.txt
nectar2p-1.2.0.dist-info/RECORD
