Metadata-Version: 2.4
Name: Nectar2P
Version: 1.2.0
Summary: A secure P2P file transfer library with optional encryption and NAT traversal support
Home-page: https://github.com/Glimor/Nectar2P
Author: Glimor
Author-email: glimor@proton.me
Keywords: p2p file transfer,secure file sharing,end-to-end encryption,NAT traversal,AES encryption,cryptography,hole punching,firewall traversal,cross-platform
Classifier: Programming Language :: Python :: 3
Classifier: License :: OSI Approved :: MIT License
Classifier: Operating System :: OS Independent
Classifier: Intended Audience :: Developers
Classifier: Topic :: Software Development :: Libraries
Classifier: Topic :: Communications :: File Sharing
Classifier: Natural Language :: English
Requires-Python: >=3.6
License-File: LICENSE
Requires-Dist: cryptography
Requires-Dist: setuptools
Dynamic: author
Dynamic: author-email
Dynamic: classifier
Dynamic: description
Dynamic: description-content-type
Dynamic: home-page
Dynamic: keywords
Dynamic: license-file
Dynamic: requires-dist
Dynamic: requires-python
Dynamic: summary
